cmtt_python_wrapper/__init__.py
cmtt_python_wrapper/__main__.py
cmtt_python_wrapper/api.py
cmtt_python_wrapper/enums.py
cmtt_python_wrapper/settings.py
cmtt_python_wrapper-0.6.dist-info/METADATA
cmtt_python_wrapper-0.6.dist-info/RECORD
cmtt_python_wrapper-0.6.dist-info/WHEEL
cmtt_python_wrapper-0.6.dist-info/top_level.txt
