Metadata-Version: 2.1
Name: cmtt-python-wrapper
Version: 0.6
Summary: Python wrapper
Home-page: https://github.com/nenanimalsya/cmtt-python-wrapper/
Author: nenanimalsya
Author-email: nenanimalsya@example.com
License: UNKNOWN
Platform: UNKNOWN
Classifier: Programming Language :: Python :: 3.6
Classifier: License :: OSI Approved :: MIT License
Classifier: Operating System :: OS Independent
Requires-Dist: requests
Requires-Dist: aiohttp
Requires-Dist: aiofiles
Requires-Dist: asyncio
